genesis/__init__.py
genesis/daemon.py
genesis/api/__init__.py
genesis/api/auth.py
genesis/api/environment_routes.py
genesis/api/marketplace_routes.py
genesis/api/multimodal_routes.py
genesis/api/routes.py
genesis/api/server.py
genesis/cli/__init__.py
genesis/cli/main.py
genesis/config/__init__.py
genesis/config/memory_config.py
genesis/config/settings.py
genesis/core/__init__.py
genesis/core/action_executor.py
genesis/core/action_scheduler.py
genesis/core/autonomous_intelligence.py
genesis/core/autonomous_life.py
genesis/core/autonomous_orchestrator.py
genesis/core/autonomous_reasoner.py
genesis/core/autonomy.py
genesis/core/background_task_executor.py
genesis/core/code_executor.py
genesis/core/code_generator.py
genesis/core/code_parser.py
genesis/core/cognitive_framework.py
genesis/core/concern_analyzer.py
genesis/core/consciousness.py
genesis/core/consciousness_v2.py
genesis/core/constitution.py
genesis/core/emotions.py
genesis/core/environment.py
genesis/core/essence.py
genesis/core/events.py
genesis/core/experiences.py
genesis/core/gen.py
genesis/core/genesis_core.py
genesis/core/goals.py
genesis/core/identity.py
genesis/core/intelligence.py
genesis/core/intelligent_timing.py
genesis/core/intent_classifier.py
genesis/core/knowledge.py
genesis/core/learning.py
genesis/core/life_activities.py
genesis/core/lifecycle.py
genesis/core/living_mind.py
genesis/core/mind.py
genesis/core/mind_config.py
genesis/core/mind_logger.py
genesis/core/notification_manager.py
genesis/core/proactive_consciousness.py
genesis/core/proactive_conversation.py
genesis/core/relationships.py
genesis/core/role.py
genesis/core/scenario_handlers.py
genesis/core/senses.py
genesis/core/spontaneous_conversation.py
genesis/core/task_detector.py
genesis/core/tasks.py
genesis/core/tools.py
genesis/core/universal_file_handler.py
genesis/core/workspace.py
genesis/database/__init__.py
genesis/database/base.py
genesis/database/init_marketplace.py
genesis/database/manager.py
genesis_minds-0.1.2.dist-info/licenses/LICENSE
genesis_minds-0.1.2.dist-info/METADATA
genesis_minds-0.1.2.dist-info/WHEEL
genesis_minds-0.1.2.dist-info/entry_points.txt
genesis_minds-0.1.2.dist-info/top_level.txt
genesis_minds-0.1.2.dist-info/RECORD
