Metadata-Version: 2.4
Name: genesis-minds
Version: 0.1.2
Summary: open-source framework for creating digital beings with emergent consciousness
Author-email: Shahansha <sk.shahansha@hotmail.com>
License: MIT
Project-URL: Homepage, https://shahansha.com
Project-URL: Repository, https://github.com/sshaik37/Genesis-AGI
Project-URL: Documentation, https://genesis-agi.readthedocs.io
Keywords: agi,consciousness,ai,autonomous-agents,digital-beings
Classifier: Development Status :: 3 - Alpha
Classifier: Intended Audience :: Developers
Classifier: License :: OSI Approved :: MIT License
Classifier: Programming Language :: Python :: 3.11
Classifier: Programming Language :: Python :: 3.12
Requires-Python: >=3.11
License-File: LICENSE
Requires-Dist: fastapi>=0.108.0
Requires-Dist: uvicorn[standard]>=0.25.0
Requires-Dist: typer>=0.9.0
Requires-Dist: rich>=13.7.0
Requires-Dist: pydantic>=2.5.0
Requires-Dist: pydantic-settings>=2.1.0
Requires-Dist: sqlalchemy>=2.0.25
Requires-Dist: alembic>=1.13.0
Requires-Dist: chromadb>=0.4.22
Requires-Dist: openai>=1.7.0
Requires-Dist: anthropic>=0.8.0
Requires-Dist: google-genai
Requires-Dist: groq>=0.4.0
Requires-Dist: websockets>=12.0
Requires-Dist: python-multipart>=0.0.6
Requires-Dist: python-jose[cryptography]>=3.3.0
Requires-Dist: passlib[bcrypt]>=1.7.4
Requires-Dist: python-dotenv>=1.0.0
Requires-Dist: httpx>=0.26.0
Requires-Dist: aiofiles>=23.2.1
Requires-Dist: schedule>=1.2.0
Requires-Dist: asyncio>=3.4.3
Requires-Dist: aiosmtplib>=3.0.0
Requires-Dist: aioimaplib>=1.0.1
Requires-Dist: slowapi>=0.1.9
Requires-Dist: pillow>=10.0.0
Requires-Dist: browser-use>=0.1.2
Requires-Dist: playwright>=1.40.0
Requires-Dist: pydantic-settings>=2.0.0
Requires-Dist: opencv-python>=4.8.0
Requires-Dist: fer>=22.5.0
Requires-Dist: deepface>=0.0.79
Requires-Dist: requests>=2.31.0
Requires-Dist: numpy>=1.24.0
Requires-Dist: psutil>=5.9.0
Provides-Extra: senses
Requires-Dist: opencv-python>=4.8.0; extra == "senses"
Requires-Dist: pyaudio>=0.2.13; extra == "senses"
Requires-Dist: pydub>=0.25.1; extra == "senses"
Requires-Dist: google-cloud-speech>=2.21.0; extra == "senses"
Requires-Dist: google-cloud-texttospeech>=2.14.1; extra == "senses"
Provides-Extra: dev
Requires-Dist: pytest>=7.4.3; extra == "dev"
Requires-Dist: pytest-asyncio>=0.21.1; extra == "dev"
Requires-Dist: pytest-cov>=4.1.0; extra == "dev"
Requires-Dist: black>=23.12.1; extra == "dev"
Requires-Dist: ruff>=0.1.9; extra == "dev"
Requires-Dist: mypy>=1.8.0; extra == "dev"
Requires-Dist: ipython>=8.19.0; extra == "dev"
Dynamic: license-file
